parrot/__init__.py
parrot/text_processing.py
parrot_nlp-0.0.8.dist-info/LICENSE
parrot_nlp-0.0.8.dist-info/METADATA
parrot_nlp-0.0.8.dist-info/WHEEL
parrot_nlp-0.0.8.dist-info/top_level.txt
parrot_nlp-0.0.8.dist-info/RECORD
