Metadata-Version: 2.1
Name: parrot-nlp
Version: 0.0.8
Summary: elegant NLP solutions and visualizations
Home-page: https://github.com/tsaruggan/parrot
Author: tsaruggan
Author-email: tsaruggan@gmail.com
License: MIT
License-File: LICENSE
Requires-Dist: nltk
Requires-Dist: contractions
